<?xml version="1.0" encoding="utf-8"?>
<LanguageData>
  <!--The following translations were generated by https://www.deepl.com/-->
  <VNPE.MustOverBed>Muss über einem Bett oder einem betretbaren Gebäude angebracht werden.</VNPE.MustOverBed>
  <VNPE.StorageSetting>Zeichnung stoppen, wenn der Speicher {0} voll ist</VNPE.StorageSetting>
  <VNPE.AutoBlood>Automatisch Blut abnehmen **</VNPE.AutoBlood>
  <VNPE.Transfuse>Blut transfundieren</VNPE.Transfuse>
  <VNPE.TransfuseSetting>Transfundieren, wenn der Bauer {0} Blut oder weniger hat</VNPE.TransfuseSetting>
  <VNPE.FillUp>Füllen Sie sie bis zu {0}*</VNPE.FillUp>
  <VNPE.HemogenInfo>(*) eine Hämogenpackung fügt 35% hinzu, so dass der Betrag nicht exakt ist</VNPE.HemogenInfo>
  <VNPE.FarmInfo>(**) Die Art der Gefangeneninteraktion sollte auf "Hämogenfarm" eingestellt werden.</VNPE.FarmInfo>
  <VNPE.Occupants>BedConnector: {0} Pfand(e)</VNPE.Occupants>
  <VNPE.CurrentModVersion>Installierte Mod-Version: {0}</VNPE.CurrentModVersion>
</LanguageData>